CL/Cute.py
CL/__init__.py
CL/config.py
CL/Display/OCCViewer.pyd
CL/Display/SimpleGui.pyd
CL/Display/__init__.py
CL/Display/backend.py
CL/Display/qtDisplay.pyd
CL/Display/icons/cursor_magnify.pyd
CL/Display/icons/cursor_magnify_area.pyd
CL/Display/icons/cursor_pan.pyd
CL/Display/icons/cursor_rotate.pyd
CL/Machine/__init__.py
CL/Machine/hans_5axis.pyd
CL/Machine/hans_5axis_a_brep.pyd
CL/Machine/hans_5axis_c_brep.pyd
CL/Machine/hans_fast.pyd
CL/Machine/hans_fast_a_brep.pyd
CL/Machine/hg_5axis.pyd
CL/Machine/hg_5axis_a_brep.pyd
CL/Machine/hg_5axis_c_brep.pyd
CL/Machine/init.py
CL/Machine/vz10.pyd
CL/Machine/vz10_a_brep.pyd
CL/Machine/vz10_c_brep.pyd
CL/Machine/yw_5axis.pyd
CL/Preprocessor/Huagong.pyd
CL/Preprocessor/Vz10.pyd
CL/Preprocessor/Yawei.pyd
CL/Preprocessor/__init__.py
CL/Preprocessor/hans_5axis_beckhoff.pyd
CL/Preprocessor/hans_5axis_siemens.pyd
CL/Preprocessor/init.py
CL/lib/Action.pyd
CL/lib/Base.pyd
CL/lib/Check.pyd
CL/lib/Editor.pyd
CL/lib/Editor2.pyd
CL/lib/Editor_Add_Point.pyd
CL/lib/Editor_Del_Point.pyd
CL/lib/Editor_Edge.pyd
CL/lib/Editor_Move.pyd
CL/lib/Editor_Rotate.pyd
CL/lib/File.pyd
CL/lib/Filter.pyd
CL/lib/Menu.pyd
CL/lib/Modify_AC.pyd
CL/lib/Path.pyd
CL/lib/Simulation.pyd
CL/lib/Syn_sim.pyd
CL/lib/View.pyd
CL/lib/__init__.py
CL/process/MakeShape.pyd
CL/process/RapidFeedUpdate.pyd
CL/process/__init__.py
CL/process/initGui.py
CL/res/__init__.py
CL/res/dark_blue_qss.py
CL/res/dark_rc.py
CL/res/icon_rc.py
CL/ui/__init__.py
CL/ui/about_ui.py
CL/ui/add_point_ui.py
CL/ui/all_UI.py
CL/ui/del_point_ui.py
CL/ui/edit_ac_ui.py
CL/ui/edit_edge_ui.py
CL/ui/geo_edit_ui.py
CL/ui/mainwindow.py
CL/ui/nc_block_edit_ui.py
CL/ui/nc_output_ui.py
CL/ui/point.py
CL/ui/simulation_ui.py
CL/ui/wire_move_edit_ui.py
CL/ui/wire_rotate_edit_ui.py
CL3d-1.0.10.dist-info/METADATA
CL3d-1.0.10.dist-info/WHEEL
CL3d-1.0.10.dist-info/top_level.txt
CL3d-1.0.10.dist-info/RECORD
